ol_themed_jupyter/__init__.py
ol_themed_jupyter/_version.py
ol_themed_jupyter/labextension/package.json
ol_themed_jupyter/labextension/static/180.cd7cddbe12cb074d0641.js
ol_themed_jupyter/labextension/static/728.247b20a0f63e766bbd06.js
ol_themed_jupyter/labextension/static/remoteEntry.83304a73106744691ca0.js
ol_themed_jupyter/labextension/static/style.js
ol_themed_jupyter/labextension/static/third-party-licenses.json
ol_themed_jupyter-0.1.1.data/data/share/jupyter/labextensions/ol-themed-jupyter/package.json
ol_themed_jupyter-0.1.1.data/data/share/jupyter/labextensions/ol-themed-jupyter/static/180.cd7cddbe12cb074d0641.js
ol_themed_jupyter-0.1.1.data/data/share/jupyter/labextensions/ol-themed-jupyter/static/728.247b20a0f63e766bbd06.js
ol_themed_jupyter-0.1.1.data/data/share/jupyter/labextensions/ol-themed-jupyter/static/remoteEntry.83304a73106744691ca0.js
ol_themed_jupyter-0.1.1.data/data/share/jupyter/labextensions/ol-themed-jupyter/static/style.js
ol_themed_jupyter-0.1.1.data/data/share/jupyter/labextensions/ol-themed-jupyter/static/third-party-licenses.json
ol_themed_jupyter-0.1.1.data/data/share/jupyter/labextensions/ol-themed-jupyter/install.json
ol_themed_jupyter-0.1.1.dist-info/METADATA
ol_themed_jupyter-0.1.1.dist-info/WHEEL
ol_themed_jupyter-0.1.1.dist-info/licenses/LICENSE
ol_themed_jupyter-0.1.1.dist-info/RECORD
